llm_ensemble/__init__.py
llm_ensemble/consensus.py
llm_ensemble/run_llm.py
llm_ensemble/prompts/judge.prompt
llm_ensemble/schemas/__init__.py
llm_ensemble/schemas/schemas.py
llm_ensemble/utils/__init__.py
llm_ensemble/utils/tavily_tool.py
llm_ensemble/utils/utils.py
multi_llm_consensus-0.1.6.dist-info/METADATA
multi_llm_consensus-0.1.6.dist-info/WHEEL
multi_llm_consensus-0.1.6.dist-info/licenses/LICENSE
multi_llm_consensus-0.1.6.dist-info/RECORD
