Metadata-Version: 2.4
Name: multi-llm-consensus
Version: 0.1.6
Summary: Achieve consensus across multiple LLMs through an AI judge coordinator
Project-URL: Homepage, https://github.com/zzzrbx/llm-ensemble
Project-URL: Repository, https://github.com/zzzrbx/llm-ensemble
Project-URL: Issues, https://github.com/zzzrbx/llm-ensemble/issues
Author-email: Roberto Pagliari <roberto.pagliari@gmail.com>
License: MIT
License-File: LICENSE
Keywords: agent,ai,consensus,langchain,langgraph,llm,multi-model
Classifier: Development Status :: 3 - Alpha
Classifier: Intended Audience :: Developers
Classifier: License :: OSI Approved :: MIT License
Classifier: Programming Language :: Python :: 3
Classifier: Programming Language :: Python :: 3.12
Classifier: Topic :: Scientific/Engineering :: Artificial Intelligence
Requires-Python: >=3.12
Requires-Dist: deepagents>=0.1.0
Requires-Dist: langchain-anthropic>=1.3.1
Requires-Dist: langchain-community>=0.4.1
Requires-Dist: langchain-google-genai>=4.1.3
Requires-Dist: langchain-openai>=1.1.7
Requires-Dist: langchain-xai>=1.2.1
Requires-Dist: langchain>=1.2.3
Requires-Dist: langgraph>=1.0.5
Requires-Dist: pydantic>=2.12.5
Requires-Dist: python-dotenv>=1.2.1
Requires-Dist: rich>=14.2.0
Requires-Dist: tavily-python>=0.7.17
